{
  "TestimonialData": [
    {
      "id": 2,
      "logoLight": "/images/made_in_courtage_logo.png",
      "logoDark": "/images/made_in_courtage_logo.png",
      "testimonial": "Un immense BRAVO à Yasmina qui a su comprendre nos besoins, reformuler nos envies et nous livrer dans un temps record notre assistant juridique dopé à l'IA !",
      "date": "",
      "author": {
        "name": "Eric",
        "designation": "Made In Courtage",
        "image": "/images/eric_debese_avatar.jpg"
      }
    },
    {
      "id": 1,
      "logoLight": "/images/kilome_logo.png",
      "logoDark": "/images/kilome_logo.png",
      "testimonial": "Merci Yasmina pour la formation, que j'ai trouvée vraiment top. Les différents modules étaient très clairs et concrets, et répondaient parfaitement à mes attentes.",
      "date": "",
      "author": {
        "name": "Jaafar",
        "designation": "Kilome",
        "image": "/images/jaafar_avatar.webp"
      }
    },
    {
      "id": 3,
      "logoLight": "/images/fit_routine_logo.png",
      "logoDark": "/images/fit_routine_logo.png",
      "testimonial": "Justin a cette force de comprendre nos besoins. Il veut comprendre de A à Z comment fonctionne ton activité pour bien savoir quel plan mettre en place. Je recommande à 1000 % les compétences de Justin pour la qualité de son travail et son professionnalisme hors pair.",
      "date": "",
      "author": {
        "name": "Nicolas",
        "designation": "Fit Routine",
        "image": ""
      }
    },
    {
      "id": 6,
      "logoLight": "/images/pharmassist_logo.png",
      "logoDark": "/images/pharmassist_logo.png",
      "testimonial": "Non seulement Yasmina est une fine pédagogue mais surtout sa capacité à prendre en charge avec douceur toutes mes demandes m'a immédiatement rassuré. Aujourd'hui, j'ai des bases solides et une furieuse envie de faire par moi-même en toute autonomie.",
      "date": "",
      "author": {
        "name": "Mat",
        "designation": "Formation IA",
        "image": ""
      }
    },

    {
      "id": 4,
      "logoLight": null,
      "logoDark": null,
      "testimonial": "Merci Yasmina encore pour cette conférence sur l'intelligence artificielle c'était vraiment enrichissant, très précis et surtout accessible. Un vrai plus… ta clarté et la fluidité de ta présentation : on suit facilement, même sur des sujets parfois techniques.",
      "date": "",
      "author": {
        "name": "Florent",
        "designation": "Conférence IA",
        "image": ""
      }
    },
    {
      "id": 5,
      "logoLight": null,
      "logoDark": null,
      "testimonial": "Merci beaucoup Yasmina pour cette conférence inspirante et très éclairante. Tu as su rendre concrète et accessible l'importance, pour les entreprises, d'accueillir l'IA dès aujourd'hui. Un grand merci pour la clarté, la pédagogie et l'élan que tu nous transmets.",
      "date": "",
      "author": {
        "name": "Une participante",
        "designation": "Masterclass IA",
        "image": ""
      }
    }
  ]
}
